CHANGES.txt
LICENSE
NOTICE
README.txt
bootstrap.py
buildout.cfg
setup.py
example/bootstrap.py
example/buildout.cfg
example/setup.py
example/app/admin.py
example/app/app.yaml
example/app/environment.py
example/app/index.yaml
example/app/main.py
example/app/tests.py
example/app/views.txt
example/app/static/favicon.ico
example/app/templates/index.html
src/lovely/__init__.py
src/lovely.gae.egg-info/PKG-INFO
src/lovely.gae.egg-info/SOURCES.txt
src/lovely.gae.egg-info/dependency_links.txt
src/lovely.gae.egg-info/namespace_packages.txt
src/lovely.gae.egg-info/requires.txt
src/lovely.gae.egg-info/top_level.txt
src/lovely.gae.egg-info/zip-safe
src/lovely/gae/__init__.py
src/lovely/gae/environment.py
src/lovely/gae/async/README.txt
src/lovely/gae/async/__init__.py
src/lovely/gae/async/tests.py
src/lovely/gae/batch/README.txt
src/lovely/gae/batch/__init__.py
src/lovely/gae/batch/tests.py
src/lovely/gae/db/__init__.py
src/lovely/gae/db/property.py
src/lovely/gae/db/property.txt
src/lovely/gae/db/tests.py
src/lovely/gae/testing/__init__.py