Metadata-Version: 1.0
Name: lovely.gae
Version: 1.0.0a1
Summary: Appengine related Python Packages from Lovely Systems
Home-page: http://code.google.com/p/lovely-gae/
Author: Lovely Systems
Author-email: office@lovelysystems.com
License: Apache License 2.0
Keywords: appengine datastore backup batch utilities
Platform: UNKNOWN
